agentgate/__init__.py
agentgate/cli.py
agentgate/agents/base.py
agentgate/agents/runner.py
agentgate/agents/simple_openai_agent.py
agentgate/core/__init__.py
agentgate/core/base_protocol.py
agentgate/core/base_protocol_adapter.py
agentgate/core/client.py
agentgate/core/connector.py
agentgate/core/network.py
agentgate/core/system_commands.py
agentgate/launchers/__init__.py
agentgate/launchers/discovery_connector.py
agentgate/launchers/network_launcher.py
agentgate/launchers/terminal_console.py
agentgate/models/__init__.py
agentgate/models/manifest.py
agentgate/models/message_thread.py
agentgate/models/messages.py
agentgate/models/network_config.py
agentgate/models/network_profile.py
agentgate/models/tool.py
agentgate/protocols/__init__.py
agentgate/protocols/communication/__init__.py
agentgate/protocols/communication/simple_messaging/__init__.py
agentgate/protocols/communication/simple_messaging/adapter.py
agentgate/protocols/communication/simple_messaging/protocol.py
agentgate/protocols/discovery/__init__.py
agentgate/protocols/discovery/agent_discovery/__init__.py
agentgate/protocols/discovery/agent_discovery/adapter.py
agentgate/protocols/discovery/agent_discovery/protocol.py
agentgate/utils/__init__.py
agentgate/utils/message_util.py
agentgate/utils/network_discovey.py
agentgate/utils/protocol_loaders.py
agentgate-0.4.0.dist-info/licenses/LICENSE
openagents/__init__.py
openagents/cli.py
openagents/agents/base.py
openagents/agents/runner.py
openagents/agents/simple_openai_agent.py
openagents/core/__init__.py
openagents/core/base_protocol.py
openagents/core/base_protocol_adapter.py
openagents/core/client.py
openagents/core/connector.py
openagents/core/network.py
openagents/core/system_commands.py
openagents/launchers/__init__.py
openagents/launchers/discovery_connector.py
openagents/launchers/network_launcher.py
openagents/launchers/terminal_console.py
openagents/models/__init__.py
openagents/models/manifest.py
openagents/models/message_thread.py
openagents/models/messages.py
agentgate-0.4.0.dist-info/METADATA
agentgate-0.4.0.dist-info/WHEEL
agentgate-0.4.0.dist-info/entry_points.txt
agentgate-0.4.0.dist-info/top_level.txt
agentgate-0.4.0.dist-info/RECORD
